<?xml version="1.0" standalone="yes"?>
<rhythmdb version="2.0">
  <entry type="iradio">
    <title>GotRadio - Forever Fifties</title>
    <genre>50s</genre>
    <artist></artist>
    <album></album>
    <location>http://pureplay.cdnstream1.com/6005_128.mp3</location>
    <rating>4</rating>
    <play-count>3</play-count>
    <last-played>1566054139</last-played>
    <bitrate>128</bitrate>
    <date>0</date>
    <media-type>application/octet-stream</media-type>
  </entry>
  <entry type="iradio">
    <title>Air Telugu 0n0</title>
    <genre>Telugu</genre>
    <artist></artist>
    <album></album>
    <location>http://airtelugu-lh.akamaihd.net/i/airtelugu_1@507818/master.m3u8</location>
    <rating>3</rating>
    <play-count>5</play-count>
    <last-played>1567311965</last-played>
    <bitrate>46</bitrate>
    <date>0</date>
    <media-type>application/octet-stream</media-type>
  </entry>
  <entry type="iradio">
    <title>reprezent [*]</title>
    <genre>Grime</genre>
    <artist></artist>
    <album></album>
    <location>http://radio.canstream.co.uk:8022/live.mp3</location>
    <rating>3</rating>
    <play-count>9</play-count>
    <last-played>1567326435</last-played>
    <bitrate>128</bitrate>
    <date>0</date>
    <media-type>application/octet-stream</media-type>
  </entry>
  <entry type="iradio">
    <title>Radio Caprice - Math Metal</title>
    <genre>Math Metal</genre>
    <artist></artist>
    <album></album>
    <location>http://79.120.39.202:9115/</location>
    <rating>4</rating>
    <play-count>5</play-count>
    <last-played>1547058046</last-played>
    <bitrate>46</bitrate>
    <date>0</date>
    <media-type>application/octet-stream</media-type>
  </entry>
  <entry type="iradio">
    <title>GotRadio - Bluegrass</title>
    <genre>Bluegrass</genre>
    <artist></artist>
    <album></album>
    <location>http://pureplay.cdnstream1.com/6000_128.mp3</location>
    <rating>4</rating>
    <play-count>2</play-count>
    <last-played>1558197326</last-played>
    <bitrate>128</bitrate>
    <date>0</date>
    <media-type>application/octet-stream</media-type>
  </entry>
  <entry type="iradio">
    <title>Radio Sharda 0n0</title>
    <genre>Kashiri</genre>
    <artist></artist>
    <album></album>
    <location>http://stream.zenolive.com/g4ua0b105eeuv</location>
    <rating>1</rating>
    <play-count>12</play-count>
    <last-played>1567331601</last-played>
    <bitrate>64</bitrate>
    <date>0</date>
    <media-type>application/octet-stream</media-type>
  </entry>
  <entry type="iradio">
    <title>Radio Paradise Rock</title>
    <genre>Eclectic | Rock</genre>
    <artist></artist>
    <album></album>
    <location>http://stream.radioparadise.com/rock-320</location>
    <rating>5</rating>
    <play-count>1</play-count>
    <last-played>1567330083</last-played>
    <bitrate>318</bitrate>
    <date>0</date>
    <media-type>application/octet-stream</media-type>
  </entry>
  <entry type="iradio">
    <title>CALM RADIO - ALOHA - Sampler</title>
    <genre>World | Pacific | Hawaiian</genre>
    <artist></artist>
    <album></album>
    <location>http://streams.calmradio.com:15728/stream</location>
    <rating>3</rating>
    <play-count>4</play-count>
    <last-played>1566036403</last-played>
    <bitrate>128</bitrate>
    <date>0</date>
    <media-type>application/octet-stream</media-type>
  </entry>
  <entry type="iradio">
    <title>Radio Caprice - Sludge Metal</title>
    <genre>Sludge Metal</genre>
    <artist></artist>
    <album></album>
    <location>http://79.120.77.11:9087/</location>
    <rating>3</rating>
    <play-count>7</play-count>
    <last-played>1567338956</last-played>
    <bitrate>46</bitrate>
    <date>0</date>
    <media-type>application/octet-stream</media-type>
  </entry>
  <entry type="iradio">
    <title>GotRadio - Hip Hop Stop</title>
    <genre>Hip Hop</genre>
    <artist></artist>
    <album></album>
    <location>http://pureplay.cdnstream1.com/6041_128.mp3</location>
    <rating>3</rating>
    <play-count>4</play-count>
    <last-played>1566296482</last-played>
    <bitrate>128</bitrate>
    <date>0</date>
    <media-type>application/octet-stream</media-type>
  </entry>
  <entry type="iradio">
    <title>GotRadio - Folk Lore</title>
    <genre>Folk Lore</genre>
    <artist></artist>
    <album></album>
    <location>http://pureplay.cdnstream1.com/6001_128.mp3</location>
    <rating>3</rating>
    <play-count>5</play-count>
    <last-played>1567340008</last-played>
    <bitrate>128</bitrate>
    <date>0</date>
    <media-type>application/octet-stream</media-type>
  </entry>
  <entry type="iradio">
    <title>ARNAVUTLARIN SESI</title>
    <genre>Shiptar Albanian</genre>
    <artist></artist>
    <album></album>
    <location>http://31.192.215.196:9952/listen.pls</location>
    <rating>4</rating>
    <play-count>16</play-count>
    <last-played>1566099415</last-played>
    <bitrate>63</bitrate>
    <date>0</date>
    <media-type>application/octet-stream</media-type>
  </entry>
  <entry type="iradio">
    <title>Beat Blender [SomaFM]</title>
    <genre>Downtempo | House | Techno</genre>
    <artist></artist>
    <album></album>
    <location>http://somafm.com/beatblender.pls</location>
    <rating>4</rating>
    <play-count>14</play-count>
    <last-played>1566028724</last-played>
    <bitrate>128</bitrate>
    <date>0</date>
    <media-type>application/octet-stream</media-type>
  </entry>
  <entry type="iradio">
    <title>AIR Tamil [*]</title>
    <genre>Tamil</genre>
    <artist></artist>
    <album></album>
    <location>http://airtamil-lh.akamaihd.net/i/airtamil_1@507817/master.m3u8</location>
    <rating>4</rating>
    <play-count>7</play-count>
    <last-played>1567311962</last-played>
    <bitrate>48</bitrate>
    <date>0</date>
    <media-type>application/octet-stream</media-type>
  </entry>
  <entry type="iradio">
    <title>Radio Caprice - Hard Rock</title>
    <genre>Hard Rock</genre>
    <artist></artist>
    <album></album>
    <location>http://79.120.77.11:9109/</location>
    <rating>2</rating>
    <play-count>9</play-count>
    <last-played>1567868052</last-played>
    <bitrate>48</bitrate>
    <date>0</date>
    <media-type>application/octet-stream</media-type>
  </entry>
  <entry type="iradio">
    <title>GotRadio - Urban Lounge</title>
    <genre>Urban</genre>
    <artist></artist>
    <album></album>
    <location>http://pureplay.cdnstream1.com/6053_64.aac</location>
    <rating>4</rating>
    <play-count>5</play-count>
    <last-played>1566055348</last-played>
    <bitrate>128</bitrate>
    <date>0</date>
    <media-type>application/octet-stream</media-type>
  </entry>
  <entry type="iradio">
    <title>GotRadio - Urban Jamz</title>
    <genre>Urban</genre>
    <artist></artist>
    <album></album>
    <location>http://pureplay.cdnstream1.com/6044_128.mp3</location>
    <rating>3</rating>
    <play-count>2</play-count>
    <last-played>1559017163</last-played>
    <bitrate>128</bitrate>
    <date>0</date>
    <media-type>application/octet-stream</media-type>
  </entry>
  <entry type="iradio">
    <title>ALLZIC09 - Blues</title>
    <genre>Blues</genre>
    <artist></artist>
    <album></album>
    <location>http://allzic09.ice.infomaniak.ch/allzic09.mp3</location>
    <rating>3</rating>
    <play-count>16</play-count>
    <last-played>1567401062</last-played>
    <bitrate>128</bitrate>
    <date>0</date>
    <media-type>application/octet-stream</media-type>
  </entry>
  <entry type="iradio">
    <title>GotRadio - Bit O' Blues</title>
    <genre>Blues</genre>
    <artist></artist>
    <album></album>
    <location>http://pureplay.cdnstream1.com/6019_128.mp3</location>
    <rating>4</rating>
    <play-count>3</play-count>
    <last-played>1566049756</last-played>
    <bitrate>128</bitrate>
    <date>0</date>
    <media-type>application/octet-stream</media-type>
  </entry>
  <entry type="iradio">
    <title>Radio Caprice - Drone Metal</title>
    <genre>See Stream Title</genre>
    <artist></artist>
    <album></album>
    <location>http://79.120.39.202:9113/</location>
    <rating>4</rating>
    <play-count>9</play-count>
    <last-played>1547058059</last-played>
    <bitrate>50</bitrate>
    <date>0</date>
    <media-type>application/octet-stream</media-type>
  </entry>
  <entry type="iradio">
    <title>Radio Caprice - Hardcore Metal</title>
    <genre>See Stream Title</genre>
    <artist></artist>
    <album></album>
    <location>http://79.111.14.76:9081/</location>
    <rating>4</rating>
    <play-count>8</play-count>
    <last-played>1547058416</last-played>
    <bitrate>46</bitrate>
    <date>0</date>
    <media-type>application/octet-stream</media-type>
  </entry>
  <entry type="iradio">
    <title>WKNC 88.1 FM (Raleigh NC)</title>
    <genre>Music</genre>
    <artist></artist>
    <album></album>
    <location>http://wknc.sma.ncsu.edu:8000/wknchq.ogg.m3u</location>
    <rating>5</rating>
    <play-count>22</play-count>
    <last-played>1545137750</last-played>
    <bitrate>112</bitrate>
    <date>0</date>
    <media-type>application/octet-stream</media-type>
  </entry>
  <entry type="iradio">
    <title>Hindi Evergreen Hits</title>
    <genre>Hindi Old</genre>
    <artist></artist>
    <album></album>
    <location>http://192.240.102.133:11454/stream/1/</location>
    <rating>3</rating>
    <play-count>8</play-count>
    <last-played>1567337611</last-played>
    <bitrate>32</bitrate>
    <date>0</date>
    <media-type>application/octet-stream</media-type>
  </entry>
  <entry type="iradio">
    <title>Ujala Radio NL 0n0</title>
    <genre>Hindi Old</genre>
    <artist></artist>
    <album></album>
    <location>http://stream2.ujala.nl/stream/2/listen.mp3</location>
    <rating>1</rating>
    <play-count>3</play-count>
    <last-played>1567399764</last-played>
    <bitrate>128</bitrate>
    <date>0</date>
    <media-type>application/octet-stream</media-type>
  </entry>
  <entry type="iradio">
    <title>Balamii 0n0</title>
    <genre>Electronic | Grime | Dub</genre>
    <artist></artist>
    <album></album>
    <location>http://balamii.out.airtime.pro:8000/balamii_a</location>
    <rating>3</rating>
    <play-count>13</play-count>
    <last-played>1567339013</last-played>
    <bitrate>128</bitrate>
    <date>0</date>
    <media-type>application/octet-stream</media-type>
  </entry>
  <entry type="iradio">
    <title>StartFM - 94.2MHz, Vilnius University, Lithuania</title>
    <genre>Underground</genre>
    <artist></artist>
    <album></album>
    <location>http://eteris.startfm.lt/startfm.ogg</location>
    <rating>5</rating>
    <play-count>16</play-count>
    <last-played>1567340357</last-played>
    <bitrate>64</bitrate>
    <date>0</date>
    <media-type>application/octet-stream</media-type>
  </entry>
  <entry type="iradio">
    <title>GotRadio - Big Band Land</title>
    <genre>Big Band</genre>
    <artist></artist>
    <album></album>
    <location>http://gr02.cdnstream.com:8430/</location>
    <rating>4</rating>
    <play-count>3</play-count>
    <last-played>1566048938</last-played>
    <bitrate>128</bitrate>
    <date>0</date>
    <media-type>application/octet-stream</media-type>
  </entry>
  <entry type="iradio">
    <title>Indirecte Radio Podcast</title>
    <genre>Alternative</genre>
    <artist></artist>
    <album></album>
    <location>http://cp6.digistream.info:20374/</location>
    <rating>4</rating>
    <play-count>12</play-count>
    <last-played>1547057320</last-played>
    <bitrate>128</bitrate>
    <date>0</date>
    <media-type>application/octet-stream</media-type>
  </entry>
  <entry type="iradio">
    <title>GotRadio - 90's Alternative</title>
    <genre>Alternative</genre>
    <artist></artist>
    <album></album>
    <location>http://pureplay.cdnstream1.com/6039_128.mp3</location>
    <rating>3</rating>
    <play-count>5</play-count>
    <last-played>1566631579</last-played>
    <bitrate>128</bitrate>
    <date>0</date>
    <media-type>application/octet-stream</media-type>
  </entry>
  <entry type="iradio">
    <title>VUR-SFM, 94.2 MHz [Vilnius]</title>
    <genre>Alternative</genre>
    <artist></artist>
    <album></album>
    <location>http://radijas2.vu.lt:8000/startfm.mp3</location>
    <rating>4</rating>
    <play-count>6</play-count>
    <last-played>1545329131</last-played>
    <bitrate>191</bitrate>
    <date>0</date>
    <media-type>application/octet-stream</media-type>
  </entry>
  <entry type="iradio">
    <title>GotRadio - Jazz So True</title>
    <genre>Jazz</genre>
    <artist></artist>
    <album></album>
    <location>http://pureplay.cdnstream1.com/6050_64.aac</location>
    <rating>4</rating>
    <play-count>2</play-count>
    <last-played>1559388111</last-played>
    <bitrate>61</bitrate>
    <date>0</date>
    <media-type>application/octet-stream</media-type>
  </entry>
  <entry type="iradio">
    <title>Radio Caprice - Russian Folk Rock</title>
    <genre>Russian Folk Rock</genre>
    <artist></artist>
    <album></album>
    <location>http://79.111.14.76:9099/</location>
    <rating>2</rating>
    <play-count>20</play-count>
    <last-played>1567875597</last-played>
    <bitrate>57</bitrate>
    <date>0</date>
    <media-type>application/octet-stream</media-type>
  </entry>
  <entry type="iradio">
    <title>Radio Caprice - Tango</title>
    <genre>Tango</genre>
    <artist></artist>
    <album></album>
    <location>http://79.120.39.202:9117/</location>
    <rating>4</rating>
    <play-count>13</play-count>
    <last-played>1567338930</last-played>
    <bitrate>44</bitrate>
    <date>0</date>
    <media-type>application/octet-stream</media-type>
  </entry>
  <entry type="iradio">
    <title>KeralaRadio.in</title>
    <genre>Malayalam</genre>
    <artist></artist>
    <album></album>
    <location>http://radio.hostonnet.com:8000/</location>
    <rating>4</rating>
    <play-count>23</play-count>
    <last-played>1545329082</last-played>
    <bitrate>79</bitrate>
    <date>0</date>
    <media-type>application/octet-stream</media-type>
  </entry>
  <entry type="iradio">
    <title>AIR Malayalam [*]</title>
    <genre>Malayalam</genre>
    <artist></artist>
    <album></album>
    <location>http://airmalayalam-lh.akamaihd.net/i/airmalayalam_1@507816/master.m3u8</location>
    <rating>4</rating>
    <play-count>50</play-count>
    <last-played>1567313007</last-played>
    <bitrate>46</bitrate>
    <date>0</date>
    <media-type>application/octet-stream</media-type>
  </entry>
  <entry type="iradio">
    <title>GotRadio - Studio 54 and More</title>
    <genre>Disco</genre>
    <artist></artist>
    <album></album>
    <location>http://pureplay.cdnstream1.com/6055_128.mp3</location>
    <rating>3</rating>
    <play-count>2</play-count>
    <last-played>1567330892</last-played>
    <bitrate>128</bitrate>
    <date>0</date>
    <media-type>application/octet-stream</media-type>
  </entry>
  <entry type="iradio">
    <title>GotRadio - Guitar Genius</title>
    <genre>Guitar</genre>
    <artist></artist>
    <album></album>
    <location>http://pureplay.cdnstream1.com/6018_128.mp3</location>
    <rating>4</rating>
    <play-count>5</play-count>
    <last-played>1566401806</last-played>
    <bitrate>128</bitrate>
    <date>0</date>
    <media-type>application/octet-stream</media-type>
  </entry>
  <entry type="iradio">
    <title>CKYR FM Calgary 0n0</title>
    <genre>World | Asian | Indian | Punjabi | Gurbani | Talk</genre>
    <artist></artist>
    <album></album>
    <location>https://14013.live.streamtheworld.com/CKYRFM_SC</location>
    <rating>2</rating>
    <play-count>20</play-count>
    <last-played>1567417338</last-played>
    <bitrate>47</bitrate>
    <date>0</date>
    <media-type>application/octet-stream</media-type>
  </entry>
  <entry type="iradio">
    <title>Radio Caprice - Ambient</title>
    <genre>Ambient</genre>
    <artist></artist>
    <album></album>
    <location>http://79.111.119.111:9023/</location>
    <rating>4</rating>
    <play-count>16</play-count>
    <last-played>1547188059</last-played>
    <bitrate>49</bitrate>
    <date>0</date>
    <media-type>application/octet-stream</media-type>
  </entry>
  <entry type="iradio">
    <title>FUV Music AAC+</title>
    <genre>eclectic</genre>
    <artist></artist>
    <album></album>
    <location>http://www.wfuv.org/sites/all/files/streams/fuv247_64k.pls</location>
    <rating>4</rating>
    <play-count>10</play-count>
    <last-played>1566099777</last-played>
    <bitrate>57</bitrate>
    <date>0</date>
    <media-type>application/octet-stream</media-type>
  </entry>
  <entry type="iradio">
    <title>psyradio * fm</title>
    <genre>psytrance goa tribal</genre>
    <artist></artist>
    <album></album>
    <location>http://streamer.psyradio.org:8130/listen.pls</location>
    <rating>4</rating>
    <play-count>13</play-count>
    <last-played>1545328686</last-played>
    <bitrate>39</bitrate>
    <date>0</date>
    <media-type>application/octet-stream</media-type>
  </entry>
  <entry type="iradio">
    <title>Radio Caprice - IDM</title>
    <genre>IDM</genre>
    <artist></artist>
    <album></album>
    <location>http://79.111.14.76:9003/</location>
    <rating>4</rating>
    <play-count>9</play-count>
    <last-played>1567852028</last-played>
    <bitrate>44</bitrate>
    <date>0</date>
    <media-type>application/octet-stream</media-type>
  </entry>
  <entry type="iradio">
    <title>Radio Caprice - Melodic Black Metal</title>
    <genre>Melodic Black Metal</genre>
    <artist></artist>
    <album></album>
    <location>http://79.111.119.111:9079/</location>
    <rating>3</rating>
    <play-count>14</play-count>
    <last-played>1567410377</last-played>
    <bitrate>45</bitrate>
    <date>0</date>
    <media-type>application/octet-stream</media-type>
  </entry>
  <entry type="iradio">
    <title>Radio Caprice - Salsa</title>
    <genre>Salsa</genre>
    <artist></artist>
    <album></album>
    <location>http://79.120.39.202:9049/</location>
    <rating>3</rating>
    <play-count>7</play-count>
    <last-played>1567338831</last-played>
    <bitrate>55</bitrate>
    <date>0</date>
    <media-type>application/octet-stream</media-type>
  </entry>
  <entry type="iradio">
    <title>WITR 89.7 - The Pulse of Music)</title>
    <genre>alternative</genre>
    <artist></artist>
    <album></album>
    <location>https://witr.rit.edu/live.m3u</location>
    <rating>4</rating>
    <play-count>19</play-count>
    <last-played>1545134826</last-played>
    <bitrate>192</bitrate>
    <date>0</date>
    <media-type>application/octet-stream</media-type>
  </entry>
  <entry type="iradio">
    <title>GotRadio - Americana</title>
    <genre>Americana</genre>
    <artist></artist>
    <album></album>
    <location>http://pureplay.cdnstream1.com/6046_128.mp3</location>
    <rating>3</rating>
    <play-count>4</play-count>
    <last-played>1566102066</last-played>
    <bitrate>128</bitrate>
    <date>0</date>
    <media-type>application/octet-stream</media-type>
  </entry>
  <entry type="iradio">
    <title>Radio Caprice - Ambient Techno</title>
    <genre>Ambient Techno</genre>
    <artist></artist>
    <album></album>
    <location>http://79.120.77.11:9153/</location>
    <rating>5</rating>
    <play-count>6</play-count>
    <last-played>1545135429</last-played>
    <bitrate>39</bitrate>
    <date>0</date>
    <media-type>application/octet-stream</media-type>
  </entry>
  <entry type="iradio">
    <title>METAL ARENA</title>
    <genre>Blackmetal, Heavymetal, Progressivemetal, Speedmetal</genre>
    <artist></artist>
    <album></album>
    <location>https://www.radioking.com/play/metal-arena</location>
    <rating>3</rating>
    <play-count>2</play-count>
    <last-played>1547189605</last-played>
    <bitrate>128</bitrate>
    <date>0</date>
    <media-type>application/octet-stream</media-type>
  </entry>
  <entry type="iradio">
    <title>Radio Rock Laut FM</title>
    <genre>German | Rock | Metal</genre>
    <artist></artist>
    <album></album>
    <location>http://stream.laut.fm/radio-rock-fm.pls</location>
    <rating>4</rating>
    <play-count>5</play-count>
    <last-played>1567330722</last-played>
    <bitrate>127</bitrate>
    <date>0</date>
    <media-type>application/octet-stream</media-type>
  </entry>
  <entry type="iradio">
    <title>56780 Radio (128K AAC+)</title>
    <genre>Oldies</genre>
    <artist></artist>
    <album></album>
    <location>http://208.131.139.148:8056/stream</location>
    <play-count>1</play-count>
    <last-played>1567877937</last-played>
    <bitrate>61</bitrate>
    <date>0</date>
    <media-type>application/octet-stream</media-type>
  </entry>
  <entry type="iradio">
    <title>WQXR: New York's Classical Music Station - MP3</title>
    <genre>Various</genre>
    <artist></artist>
    <album></album>
    <location>https://stream.wqxr.org/wqxr-web</location>
    <rating>3</rating>
    <play-count>5</play-count>
    <last-played>1547189718</last-played>
    <bitrate>64</bitrate>
    <date>0</date>
    <media-type>application/octet-stream</media-type>
  </entry>
  <entry type="iradio">
    <title>KCRW Live</title>
    <genre>Various</genre>
    <artist></artist>
    <album></album>
    <location>https://kcrw.streamguys1.com/kcrw_192k_mp3_on_air</location>
    <rating>4</rating>
    <play-count>10</play-count>
    <last-played>1558017161</last-played>
    <bitrate>191</bitrate>
    <date>0</date>
    <media-type>application/octet-stream</media-type>
  </entry>
  <entry type="iradio">
    <title>KUSF</title>
    <genre>Rock</genre>
    <artist></artist>
    <album></album>
    <location>http://104.236.145.45:8000/stream</location>
    <rating>3</rating>
    <play-count>17</play-count>
    <last-played>1567418141</last-played>
    <bitrate>128</bitrate>
    <date>0</date>
    <media-type>application/octet-stream</media-type>
  </entry>
  <entry type="iradio">
    <title>Radio Caprice - Power Metal</title>
    <genre>Power Metal</genre>
    <artist></artist>
    <album></album>
    <location>http://79.120.77.11:9099/</location>
    <rating>4</rating>
    <play-count>5</play-count>
    <last-played>1559971968</last-played>
    <bitrate>63</bitrate>
    <date>0</date>
    <media-type>application/octet-stream</media-type>
  </entry>
  <entry type="iradio">
    <title>Radio Samleng Khemara 0n0</title>
    <genre>Cambodian |Khmer Oldies</genre>
    <artist></artist>
    <album></album>
    <location>http://167.114.64.181:8570/;</location>
    <rating>3</rating>
    <play-count>5</play-count>
    <last-played>1567331183</last-played>
    <bitrate>64</bitrate>
    <date>0</date>
    <media-type>application/octet-stream</media-type>
  </entry>
  <entry type="iradio">
    <title>Radio Caprice - Post Hardcore</title>
    <genre>Post Hardcore</genre>
    <artist></artist>
    <album></album>
    <location>http://79.111.119.111:9087/</location>
    <rating>2</rating>
    <play-count>12</play-count>
    <last-played>1567337714</last-played>
    <bitrate>39</bitrate>
    <date>0</date>
    <media-type>application/octet-stream</media-type>
  </entry>
  <entry type="iradio">
    <title>NTS Live [*]</title>
    <genre>Eclectic | Experimental</genre>
    <artist></artist>
    <album></album>
    <location>https://stream-relay-geo.ntslive.net/stream</location>
    <rating>4</rating>
    <play-count>12</play-count>
    <last-played>1567847693</last-played>
    <bitrate>128</bitrate>
    <date>0</date>
    <media-type>application/octet-stream</media-type>
  </entry>
  <entry type="iradio">
    <title>NTS Radio 2</title>
    <genre>Eclectic | Experimental</genre>
    <artist></artist>
    <album></album>
    <location>https://stream-relay-geo.ntslive.net/stream2</location>
    <rating>4</rating>
    <play-count>1</play-count>
    <last-played>1567330549</last-played>
    <bitrate>127</bitrate>
    <date>0</date>
    <media-type>application/octet-stream</media-type>
  </entry>
  <entry type="iradio">
    <title>Radio Caprice - Post Metal</title>
    <genre>Post Metal</genre>
    <artist></artist>
    <album></album>
    <location>http://79.120.39.202:9119/</location>
    <rating>4</rating>
    <play-count>5</play-count>
    <last-played>1547058015</last-played>
    <bitrate>46</bitrate>
    <date>0</date>
    <media-type>application/octet-stream</media-type>
  </entry>
  <entry type="iradio">
    <title>WHRB Havard HE-AAC Stream</title>
    <genre>Other</genre>
    <artist></artist>
    <album></album>
    <location>http://player.whrb.org/listen-aac.pls</location>
    <rating>4</rating>
    <play-count>2</play-count>
    <last-played>1548781313</last-played>
    <bitrate>61</bitrate>
    <date>0</date>
    <media-type>application/octet-stream</media-type>
  </entry>
  <entry type="iradio">
    <title>WREK Atlanta 91.1fm - Georgia Tech Student Radio [*!]</title>
    <genre>College</genre>
    <artist></artist>
    <album></album>
    <location>http://streaming.wrek.org:8000/wrek_live-128kb.m3u</location>
    <rating>3</rating>
    <play-count>24</play-count>
    <last-played>1567326423</last-played>
    <bitrate>127</bitrate>
    <date>0</date>
    <media-type>application/octet-stream</media-type>
  </entry>
  <entry type="iradio">
    <title>90.9fm WCDB Albany [TODO web]</title>
    <genre>College</genre>
    <artist></artist>
    <album></album>
    <location>http://streams.wcdbfm.com:3952/</location>
    <rating>3</rating>
    <play-count>16</play-count>
    <last-played>1566020160</last-played>
    <bitrate>128</bitrate>
    <date>0</date>
    <media-type>application/octet-stream</media-type>
  </entry>
  <entry type="iradio">
    <title>KTRU [i]</title>
    <genre>College</genre>
    <artist></artist>
    <album></album>
    <location>http://www.ktru.org/audiometa/listen4I128m3.m3u</location>
    <rating>5</rating>
    <play-count>37</play-count>
    <last-played>1567844481</last-played>
    <bitrate>126</bitrate>
    <date>0</date>
    <media-type>application/octet-stream</media-type>
  </entry>
  <entry type="iradio">
    <title>Radio Caprice - Grindcore</title>
    <genre>Grindcore</genre>
    <artist></artist>
    <album></album>
    <location>http://79.120.77.11:9115/</location>
    <rating>4</rating>
    <play-count>5</play-count>
    <last-played>1547057585</last-played>
    <bitrate>46</bitrate>
    <date>0</date>
    <media-type>application/octet-stream</media-type>
  </entry>
  <entry type="iradio">
    <title>Folk Alley</title>
    <genre>Folk</genre>
    <artist></artist>
    <album></album>
    <location>http://www.folkalley.com/folkalley-aacplus64.pls</location>
    <rating>5</rating>
    <play-count>20</play-count>
    <last-played>1567340289</last-played>
    <bitrate>66</bitrate>
    <date>0</date>
    <media-type>application/octet-stream</media-type>
  </entry>
  <entry type="iradio">
    <title>Ori&#xEB;nt Express [*]</title>
    <genre>Classical | Eastern | Indian | Carnatic | Hindustani</genre>
    <artist></artist>
    <album></album>
    <location>http://streams.greenhost.nl:8080/orientexpress</location>
    <rating>4</rating>
    <play-count>35</play-count>
    <last-played>1567310589</last-played>
    <bitrate>160</bitrate>
    <date>0</date>
    <media-type>application/octet-stream</media-type>
  </entry>
  <entry type="iradio">
    <title>M2 ROCK</title>
    <genre>Rock Alternative Metal</genre>
    <artist></artist>
    <album></album>
    <location>http://www.m2radio.fr/pls/m2rock_winamp.m3u</location>
    <rating>4</rating>
    <play-count>16</play-count>
    <last-played>1565632397</last-played>
    <bitrate>127</bitrate>
    <date>0</date>
    <media-type>application/octet-stream</media-type>
  </entry>
  <entry type="iradio">
    <title>GotRadio - Classic Country</title>
    <genre>Country</genre>
    <artist></artist>
    <album></album>
    <location>http://pureplay.cdnstream1.com/6048_128.mp3</location>
    <rating>3</rating>
    <play-count>3</play-count>
    <last-played>1566052168</last-played>
    <bitrate>128</bitrate>
    <date>0</date>
    <media-type>application/octet-stream</media-type>
  </entry>
  <entry type="iradio">
    <title>GotRadio - Texas Red Dirt</title>
    <genre>Country</genre>
    <artist></artist>
    <album></album>
    <location>http://pureplay.cdnstream1.com/6028_128.mp3</location>
    <rating>4</rating>
    <play-count>3</play-count>
    <last-played>1559022883</last-played>
    <bitrate>128</bitrate>
    <date>0</date>
    <media-type>application/octet-stream</media-type>
  </entry>
  <entry type="iradio">
    <title>GotRadio - The 60's</title>
    <genre>60s</genre>
    <artist></artist>
    <album></album>
    <location>http://pureplay.cdnstream1.com/6011_128.mp3</location>
    <rating>4</rating>
    <play-count>4</play-count>
    <last-played>1567331004</last-played>
    <bitrate>128</bitrate>
    <date>0</date>
    <media-type>application/octet-stream</media-type>
  </entry>
  <entry type="iradio">
    <title>Beyond The Beat Generation</title>
    <genre>60s</genre>
    <artist></artist>
    <album></album>
    <location>http://86.94.213.59:8000/listen.pls</location>
    <rating>4</rating>
    <play-count>15</play-count>
    <last-played>1566028797</last-played>
    <bitrate>127</bitrate>
    <date>0</date>
    <media-type>application/octet-stream</media-type>
  </entry>
  <entry type="iradio">
    <title>Radio Caprice - Latin Jazz</title>
    <genre>Latin Jazz</genre>
    <artist></artist>
    <album></album>
    <location>http://79.111.119.111:9055/</location>
    <rating>4</rating>
    <play-count>11</play-count>
    <last-played>1558172317</last-played>
    <bitrate>39</bitrate>
    <date>0</date>
    <media-type>application/octet-stream</media-type>
  </entry>
  <entry type="iradio">
    <title>Memory Radio 2</title>
    <genre>Oldies Schlager German</genre>
    <artist></artist>
    <album></album>
    <location>http://www.memoryradio.de/radio2/listen.pls</location>
    <rating>4</rating>
    <play-count>27</play-count>
    <last-played>1545133181</last-played>
    <bitrate>128</bitrate>
    <date>0</date>
    <media-type>application/octet-stream</media-type>
  </entry>
  <entry type="iradio">
    <title>Radio Caprice - Classical Baroque</title>
    <genre>Classical Baroque</genre>
    <artist></artist>
    <album></album>
    <location>http://79.111.14.76:9113/</location>
    <rating>2</rating>
    <play-count>13</play-count>
    <last-played>1567867973</last-played>
    <bitrate>46</bitrate>
    <date>0</date>
    <media-type>application/octet-stream</media-type>
  </entry>
  <entry type="iradio">
    <title>Radio Caprice - Psychedelic Rock</title>
    <genre>Psychedelic Rock</genre>
    <artist></artist>
    <album></album>
    <location>http://79.111.119.111:9027/</location>
    <rating>4</rating>
    <play-count>6</play-count>
    <last-played>1547188017</last-played>
    <bitrate>41</bitrate>
    <date>0</date>
    <media-type>application/octet-stream</media-type>
  </entry>
  <entry type="iradio">
    <title>Radio Caprice - Glitch</title>
    <genre>Glitch</genre>
    <artist></artist>
    <album></album>
    <location>http://79.111.14.76:9129/</location>
    <rating>4</rating>
    <play-count>8</play-count>
    <last-played>1548784161</last-played>
    <bitrate>41</bitrate>
    <date>0</date>
    <media-type>application/octet-stream</media-type>
  </entry>
  <entry type="iradio">
    <title>CALM RADIO - LIGHT CLASSICAL - Sampler</title>
    <genre>Classical | Baroque</genre>
    <artist></artist>
    <album></album>
    <location>http://streams.calmradio.com:21128/</location>
    <rating>3</rating>
    <play-count>8</play-count>
    <last-played>1566040614</last-played>
    <bitrate>128</bitrate>
    <date>0</date>
    <media-type>application/octet-stream</media-type>
  </entry>
  <entry type="iradio">
    <title>Radio Caprice - Atmosperic/Ambient Black Metal</title>
    <genre>Ambient Black Metal</genre>
    <artist></artist>
    <album></album>
    <location>http://79.120.39.202:9093/</location>
    <rating>3</rating>
    <play-count>8</play-count>
    <last-played>1567338866</last-played>
    <bitrate>44</bitrate>
    <date>0</date>
    <media-type>application/octet-stream</media-type>
  </entry>
  <entry type="iradio">
    <title>Radio Caprice - Symphonic Rock</title>
    <genre>Symphonic Rock</genre>
    <artist></artist>
    <album></album>
    <location>http://79.120.39.202:9067/</location>
    <rating>5</rating>
    <play-count>10</play-count>
    <last-played>1545135222</last-played>
    <bitrate>45</bitrate>
    <date>0</date>
    <media-type>application/octet-stream</media-type>
  </entry>
  <entry type="iradio">
    <title>ClassicsOn Radio</title>
    <genre>Classical</genre>
    <artist></artist>
    <album></album>
    <location>http://208.131.139.148:8035/stream</location>
    <play-count>5</play-count>
    <last-played>1567878203</last-played>
    <bitrate>126</bitrate>
    <date>0</date>
    <media-type>application/octet-stream</media-type>
  </entry>
  <entry type="iradio">
    <title>WKSU 3 Classical</title>
    <genre>Classical</genre>
    <artist></artist>
    <album></album>
    <location>http://www.wksu.org/listen/wksu3.pls</location>
    <rating>3</rating>
    <play-count>11</play-count>
    <last-played>1561194837</last-played>
    <bitrate>128</bitrate>
    <date>0</date>
    <media-type>application/octet-stream</media-type>
  </entry>
  <entry type="iradio">
    <title>BBC 6</title>
    <genre>Alternative | Indie</genre>
    <artist></artist>
    <album></album>
    <location>http://a.files.bbci.co.uk/media/live/manifesto/audio/simulcast/hls/nonuk/sbr_low/llnw/bbc_6music.m3u8</location>
    <rating>5</rating>
    <play-count>19</play-count>
    <last-played>1567417795</last-played>
    <bitrate>94</bitrate>
    <date>0</date>
    <media-type>application/octet-stream</media-type>
  </entry>
  <entry type="iradio">
    <title>BFF.fm [no title during night in US]</title>
    <genre>Pop</genre>
    <artist></artist>
    <album></album>
    <location>https://stream.bff.fm/1/BFF.fm.pls</location>
    <rating>4</rating>
    <play-count>4</play-count>
    <last-played>1567340386</last-played>
    <bitrate>128</bitrate>
    <date>0</date>
    <media-type>application/octet-stream</media-type>
  </entry>
  <entry type="iradio">
    <title>Open Drum N Bass [a]</title>
    <genre>Misc</genre>
    <artist></artist>
    <album></album>
    <location>http://stream.open.fm/41</location>
    <rating>4</rating>
    <play-count>14</play-count>
    <last-played>1546966619</last-played>
    <bitrate>44</bitrate>
    <date>0</date>
    <media-type>application/octet-stream</media-type>
  </entry>
  <entry type="iradio">
    <title>M2 CLASSIC</title>
    <genre>Soundtracks | Classical</genre>
    <artist></artist>
    <album></album>
    <location>http://www.m2radio.fr/pls/m2classic_winamp.m3u</location>
    <rating>2</rating>
    <play-count>17</play-count>
    <last-played>1567338064</last-played>
    <bitrate>127</bitrate>
    <date>0</date>
    <media-type>application/octet-stream</media-type>
  </entry>
  <entry type="iradio">
    <title>Radio Caprice - Nu-Disco</title>
    <genre>Nu-Disco</genre>
    <artist></artist>
    <album></album>
    <location>http://79.111.119.111:9081/</location>
    <rating>3</rating>
    <play-count>13</play-count>
    <last-played>1567858131</last-played>
    <bitrate>41</bitrate>
    <date>0</date>
    <media-type>application/octet-stream</media-type>
  </entry>
  <entry type="iradio">
    <title>FreshAir.org.uk [i]</title>
    <genre>Student</genre>
    <artist></artist>
    <album></album>
    <location>http://radio.freshair.org.uk/radio</location>
    <rating>4</rating>
    <play-count>7</play-count>
    <last-played>1566099732</last-played>
    <bitrate>192</bitrate>
    <date>0</date>
    <media-type>application/octet-stream</media-type>
  </entry>
  <entry type="iradio">
    <title>Shaivam Radio</title>
    <genre>Hindu Indian Devotional</genre>
    <artist></artist>
    <album></album>
    <location>http://108.59.9.147:8160/stream/1/</location>
    <play-count>3</play-count>
    <last-played>1567410640</last-played>
    <bitrate>127</bitrate>
    <date>0</date>
    <media-type>application/octet-stream</media-type>
  </entry>
  <entry type="iradio">
    <title>90.3 the Core RLC-WVPH 64k AAC+</title>
    <genre>Mixed | Rock | Metal | Hip Hop</genre>
    <artist></artist>
    <album></album>
    <location>http://165.230.36.186:8100/</location>
    <rating>4</rating>
    <play-count>7</play-count>
    <last-played>1567411529</last-played>
    <bitrate>61</bitrate>
    <date>0</date>
    <media-type>application/octet-stream</media-type>
  </entry>
  <entry type="iradio">
    <title>Radio Caprice - Progressive Death Metal</title>
    <genre>Progressive Death Metal</genre>
    <artist></artist>
    <album></album>
    <location>http://79.111.119.111:9001/</location>
    <rating>3</rating>
    <play-count>17</play-count>
    <last-played>1567408626</last-played>
    <bitrate>3458</bitrate>
    <date>0</date>
    <media-type>application/octet-stream</media-type>
  </entry>
  <entry type="iradio">
    <title>Radio Caprice - Progressive Rock</title>
    <genre>Progressive Rock</genre>
    <artist></artist>
    <album></album>
    <location>http://79.111.119.111:9121/</location>
    <rating>3</rating>
    <play-count>10</play-count>
    <last-played>1567338742</last-played>
    <bitrate>44</bitrate>
    <date>0</date>
    <media-type>application/octet-stream</media-type>
  </entry>
  <entry type="iradio">
    <title>RADIO METAL ON: The Heavy </title>
    <genre>Heavy Metal, Metal, Hard Rock</genre>
    <artist></artist>
    <album></album>
    <location>http://radiometalon.com:2199/tunein/heavy-mp3.pls</location>
    <rating>3</rating>
    <play-count>10</play-count>
    <last-played>1559051527</last-played>
    <bitrate>127</bitrate>
    <date>0</date>
    <media-type>application/octet-stream</media-type>
  </entry>
  <entry type="iradio">
    <title>Radio Caprice - Viking Metal</title>
    <genre>Viking Metal</genre>
    <artist></artist>
    <album></album>
    <location>http://79.111.14.76:9077/</location>
    <rating>3</rating>
    <play-count>11</play-count>
    <last-played>1567855880</last-played>
    <bitrate>46</bitrate>
    <date>0</date>
    <media-type>application/octet-stream</media-type>
  </entry>
  <entry type="iradio">
    <title>Electro Swing Revolution Radio</title>
    <genre>Swing</genre>
    <artist></artist>
    <album></album>
    <location>http://electroswing-radio.com/electro_swing_revolution_radio.pls</location>
    <rating>4</rating>
    <play-count>16</play-count>
    <last-played>1566041320</last-played>
    <bitrate>127</bitrate>
    <date>0</date>
    <media-type>application/octet-stream</media-type>
  </entry>
  <entry type="iradio">
    <title>XRay FM</title>
    <genre>Progressive</genre>
    <artist></artist>
    <album></album>
    <location>http://listen.xray.fm:8000/stream</location>
    <rating>4</rating>
    <play-count>12</play-count>
    <last-played>1547056769</last-played>
    <bitrate>127</bitrate>
    <date>0</date>
    <media-type>application/octet-stream</media-type>
  </entry>
  <entry type="iradio">
    <title>Radio Caprice - Middle East Music</title>
    <genre>Middle East</genre>
    <artist></artist>
    <album></album>
    <location>http://79.111.119.111:9133/</location>
    <rating>3</rating>
    <play-count>10</play-count>
    <last-played>1567338750</last-played>
    <bitrate>46</bitrate>
    <date>0</date>
    <media-type>application/octet-stream</media-type>
  </entry>
  <entry type="iradio">
    <title>Radio Caprice - Stoner Metal</title>
    <genre>Stoner Metal</genre>
    <artist></artist>
    <album></album>
    <location>http://79.120.77.11:9089/</location>
    <rating>3</rating>
    <play-count>9</play-count>
    <last-played>1567338967</last-played>
    <bitrate>48</bitrate>
    <date>0</date>
    <media-type>application/octet-stream</media-type>
  </entry>
  <entry type="iradio">
    <title>GotRadio - Jazz So Smooth</title>
    <genre>Smooth Jazz</genre>
    <artist></artist>
    <album></album>
    <location>http://pureplay.cdnstream1.com/6049_128.mp3</location>
    <rating>3</rating>
    <play-count>3</play-count>
    <last-played>1559055185</last-played>
    <bitrate>128</bitrate>
    <date>0</date>
    <media-type>application/octet-stream</media-type>
  </entry>
  <entry type="iradio">
    <title>Radio Paradise Mellow</title>
    <genre>Eclectic | Mellow</genre>
    <artist></artist>
    <album></album>
    <location>http://stream.radioparadise.com/mellow-320</location>
    <rating>5</rating>
    <play-count>1</play-count>
    <last-played>1567330040</last-played>
    <bitrate>315</bitrate>
    <date>0</date>
    <media-type>application/octet-stream</media-type>
  </entry>
  <entry type="iradio">
    <title>Radio Caprice - Oldies</title>
    <genre>Oldies 50s 60s</genre>
    <artist></artist>
    <album></album>
    <location>http://79.120.77.11:9107/</location>
    <rating>4</rating>
    <play-count>7</play-count>
    <last-played>1547057629</last-played>
    <bitrate>45</bitrate>
    <date>0</date>
    <media-type>application/octet-stream</media-type>
  </entry>
  <entry type="iradio">
    <title>Radio Caprice - Math Rock</title>
    <genre>Math Rock</genre>
    <artist></artist>
    <album></album>
    <location>http://79.120.39.202:9151/</location>
    <rating>4</rating>
    <play-count>3</play-count>
    <last-played>1547057797</last-played>
    <bitrate>53</bitrate>
    <date>0</date>
    <media-type>application/octet-stream</media-type>
  </entry>
  <entry type="iradio">
    <title>Radio Caprice - Flamenco [sp_mi]</title>
    <genre>Flamenco</genre>
    <artist></artist>
    <album></album>
    <location>http://79.111.14.76:9055/</location>
    <rating>4</rating>
    <play-count>10</play-count>
    <last-played>1547186489</last-played>
    <bitrate>44</bitrate>
    <date>0</date>
    <media-type>application/octet-stream</media-type>
  </entry>
  <entry type="iradio">
    <title>Miyurusara Radio</title>
    <genre>Sinhala</genre>
    <artist></artist>
    <album></album>
    <location>http://76.164.217.100:7282/stream?type=.mp3</location>
    <rating>4</rating>
    <play-count>1</play-count>
    <last-played>1567335243</last-played>
    <bitrate>46</bitrate>
    <date>0</date>
    <media-type>application/octet-stream</media-type>
  </entry>
  <entry type="iradio">
    <title>Radio Caprice - Classical Piano</title>
    <genre>Classical Piano</genre>
    <artist></artist>
    <album></album>
    <location>http://79.120.39.202:9069/</location>
    <rating>3</rating>
    <play-count>11</play-count>
    <last-played>1567338848</last-played>
    <bitrate>44</bitrate>
    <date>0</date>
    <media-type>application/octet-stream</media-type>
  </entry>
  <entry type="iradio">
    <title>M2 FUNK</title>
    <genre>Funk Disco 70s 80s 90s 00s</genre>
    <artist></artist>
    <album></album>
    <location>http://www.m2radio.fr/pls/m2funk_winamp.m3u</location>
    <rating>4</rating>
    <play-count>19</play-count>
    <last-played>1545145986</last-played>
    <bitrate>127</bitrate>
    <date>0</date>
    <media-type>application/octet-stream</media-type>
  </entry>
  <entry type="iradio">
    <title>KSPC 0n0</title>
    <genre>Alternative | Eclectic | Jazz</genre>
    <artist></artist>
    <album></album>
    <location>http://37.187.79.93:8419/stream192</location>
    <rating>3</rating>
    <play-count>28</play-count>
    <last-played>1567335777</last-played>
    <bitrate>192</bitrate>
    <date>0</date>
    <media-type>application/octet-stream</media-type>
  </entry>
  <entry type="iradio">
    <title>Black Label Extreme Metal Radio</title>
    <genre>Extreme Metal</genre>
    <artist></artist>
    <album></album>
    <location>http://108.61.20.171:20406/</location>
    <rating>3</rating>
    <play-count>18</play-count>
    <last-played>1567335552</last-played>
    <bitrate>128</bitrate>
    <date>0</date>
    <media-type>application/octet-stream</media-type>
  </entry>
  <entry type="iradio">
    <title>RADIO METAL ON: THRASHER</title>
    <genre>Thrash Metal, Metal</genre>
    <artist></artist>
    <album></album>
    <location>http://radiometalon.com:2199/tunein/thrasher-mp3.pls</location>
    <rating>4</rating>
    <play-count>15</play-count>
    <last-played>1557032813</last-played>
    <bitrate>127</bitrate>
    <date>0</date>
    <media-type>application/octet-stream</media-type>
  </entry>
  <entry type="iradio">
    <title>KVRX</title>
    <genre>Student | Eclectic | Alternative</genre>
    <artist></artist>
    <album></album>
    <location>http://tstv-stream.tsm.utexas.edu:8000/kvrx_livestream</location>
    <rating>2</rating>
    <play-count>10</play-count>
    <last-played>1567857873</last-played>
    <bitrate>192</bitrate>
    <date>0</date>
    <media-type>application/octet-stream</media-type>
  </entry>
  <entry type="iradio">
    <title>GotRadio - The Big Score</title>
    <genre>Soundtracks</genre>
    <artist></artist>
    <album></album>
    <location>http://pureplay.cdnstream1.com/6003_128.mp3</location>
    <rating>3</rating>
    <play-count>4</play-count>
    <last-played>1567340017</last-played>
    <bitrate>128</bitrate>
    <date>0</date>
    <media-type>application/octet-stream</media-type>
  </entry>
  <entry type="iradio">
    <title>GotRadio - Celtic Crossing</title>
    <genre>Celtic</genre>
    <artist></artist>
    <album></album>
    <location>http://pureplay.cdnstream1.com/6007_128.mp3</location>
    <rating>3</rating>
    <play-count>3</play-count>
    <last-played>1567340034</last-played>
    <bitrate>128</bitrate>
    <date>0</date>
    <media-type>application/octet-stream</media-type>
  </entry>
  <entry type="iradio">
    <title>Radio City Tamil</title>
    <genre>Tamil | Talk</genre>
    <artist></artist>
    <album></album>
    <location>http://prclive1.listenon.in:9948/;</location>
    <rating>1</rating>
    <play-count>13</play-count>
    <last-played>1567848373</last-played>
    <bitrate>96</bitrate>
    <date>0</date>
    <media-type>application/octet-stream</media-type>
  </entry>
  <entry type="iradio">
    <title>GTR.FM - Gokulam Tamil Radio</title>
    <genre>Tamil | Talk</genre>
    <artist></artist>
    <album></album>
    <location>http://eu4.fastcast4u.com:5250/</location>
    <rating>3</rating>
    <play-count>19</play-count>
    <last-played>1567339936</last-played>
    <bitrate>96</bitrate>
    <date>0</date>
    <media-type>application/octet-stream</media-type>
  </entry>
  <entry type="iradio">
    <title>GTBC Radio 0n0</title>
    <genre>Tamil | Talk</genre>
    <artist></artist>
    <album></album>
    <location>http://38.96.148.18:6150/stream/1/</location>
    <rating>3</rating>
    <play-count>5</play-count>
    <last-played>1567338176</last-played>
    <bitrate>128</bitrate>
    <date>0</date>
    <media-type>application/octet-stream</media-type>
  </entry>
  <entry type="iradio">
    <title>Radio Caprice - Hard Bop</title>
    <genre>Hard Bop Jazz</genre>
    <artist></artist>
    <album></album>
    <location>http://79.111.14.76:9047/</location>
    <rating>4</rating>
    <play-count>5</play-count>
    <last-played>1547186515</last-played>
    <bitrate>44</bitrate>
    <date>0</date>
    <media-type>application/octet-stream</media-type>
  </entry>
  <entry type="iradio">
    <title>Fairchild Radio AM1470 0n0</title>
    <genre>Chinese</genre>
    <artist></artist>
    <album></album>
    <location>http://icecast01.eseenet.com:8000/am1470</location>
    <rating>2</rating>
    <play-count>21</play-count>
    <last-played>1567331634</last-played>
    <bitrate>53</bitrate>
    <date>0</date>
    <media-type>application/octet-stream</media-type>
  </entry>
  <entry type="iradio">
    <title>BBC Asian Network</title>
    <genre>Asian | Indian</genre>
    <artist></artist>
    <album></album>
    <location>http://bbcmedia.ic.llnwd.net/stream/bbcmedia_asianet_mf_p</location>
    <rating>3</rating>
    <play-count>21</play-count>
    <last-played>1567417322</last-played>
    <bitrate>128</bitrate>
    <date>0</date>
    <media-type>application/octet-stream</media-type>
  </entry>
  <entry type="iradio">
    <title>Radio Girmit</title>
    <genre>Kannada</genre>
    <artist></artist>
    <album></album>
    <location>http://sc9.mystreamserver.com:8070/</location>
    <rating>3</rating>
    <play-count>5</play-count>
    <last-played>1508699844</last-played>
    <bitrate>64</bitrate>
    <date>0</date>
    <media-type>application/octet-stream</media-type>
  </entry>
  <entry type="iradio">
    <title>AIR Kannada 0n0</title>
    <genre>Kannada</genre>
    <artist></artist>
    <album></album>
    <location>http://airkannada-lh.akamaihd.net/i/airkannada_1@507819/master.m3u8</location>
    <rating>3</rating>
    <play-count>11</play-count>
    <last-played>1566020690</last-played>
    <bitrate>47</bitrate>
    <date>0</date>
    <media-type>application/octet-stream</media-type>
  </entry>
  <entry type="iradio">
    <title>Illinois Street Lounge [SomaFM]</title>
    <genre>Exotica Lounge</genre>
    <artist></artist>
    <album></album>
    <location>http://somafm.com/illstreet130.pls</location>
    <rating>4</rating>
    <play-count>16</play-count>
    <last-played>1545328930</last-played>
    <bitrate>124</bitrate>
    <date>0</date>
    <media-type>application/octet-stream</media-type>
  </entry>
  <entry type="iradio">
    <title>SikhNet Radio - Channel 1</title>
    <genre>Gurbani</genre>
    <artist></artist>
    <album></album>
    <location>https://www.sikhnet.com/webapps/radio/playlist.php?c=channel1&amp;m=high.pls</location>
    <play-count>2</play-count>
    <last-played>1567337587</last-played>
    <bitrate>96</bitrate>
    <date>0</date>
    <media-type>application/octet-stream</media-type>
  </entry>
  <entry type="iradio">
    <title>Onslaught Radio [1101 nw]</title>
    <genre>Metal</genre>
    <artist></artist>
    <album></album>
    <location>http://178.32.48.70:8001/</location>
    <rating>4</rating>
    <play-count>10</play-count>
    <last-played>1505096920</last-played>
    <bitrate>128</bitrate>
    <date>0</date>
    <media-type>application/octet-stream</media-type>
  </entry>
  <entry type="iradio">
    <title>Radio Caprice - Heavy / Hard Blues</title>
    <genre>Heavy / Hard Blues</genre>
    <artist></artist>
    <album></album>
    <location>http://79.120.77.11:9119/</location>
    <rating>4</rating>
    <play-count>7</play-count>
    <last-played>1558190487</last-played>
    <bitrate>53</bitrate>
    <date>0</date>
    <media-type>application/octet-stream</media-type>
  </entry>
  <entry type="iradio">
    <title>World Music Radio (WMR)</title>
    <genre>International, Reggae, Salsa, Brazilian, African</genre>
    <artist></artist>
    <album></album>
    <location>http://stream.wlmm.dk:8010/wmr</location>
    <rating>3</rating>
    <play-count>7</play-count>
    <last-played>1567408232</last-played>
    <bitrate>114</bitrate>
    <date>0</date>
    <media-type>application/octet-stream</media-type>
  </entry>
  <entry type="iradio">
    <title>RADIO METAL ON: THE BRUTAL [i]</title>
    <genre>Death Metal, Black Metal, Thrash Metal</genre>
    <artist></artist>
    <album></album>
    <location>http://radiometalon.com:2199/tunein/brutal-mp3.pls</location>
    <rating>4</rating>
    <play-count>8</play-count>
    <last-played>1545329055</last-played>
    <bitrate>127</bitrate>
    <date>0</date>
    <media-type>application/octet-stream</media-type>
  </entry>
  <entry type="iradio">
    <title>GotRadio - Reggae, Rasta and Roots</title>
    <genre>Reggae | Rasta | Roots</genre>
    <artist></artist>
    <album></album>
    <location>http://pureplay.cdnstream1.com/6051_128.mp3</location>
    <rating>3</rating>
    <play-count>5</play-count>
    <last-played>1567330833</last-played>
    <bitrate>128</bitrate>
    <date>0</date>
    <media-type>application/octet-stream</media-type>
  </entry>
  <entry type="iradio">
    <title>Radio Caprice - Technical Death Metal</title>
    <genre>Technical Death Metal</genre>
    <artist></artist>
    <album></album>
    <location>http://79.120.77.11:9095/</location>
    <rating>4</rating>
    <play-count>8</play-count>
    <last-played>1547057729</last-played>
    <bitrate>46</bitrate>
    <date>0</date>
    <media-type>application/octet-stream</media-type>
  </entry>
  <entry type="iradio">
    <title>CALM RADIO - BACHATA - Sampler</title>
    <genre>Latin | Salsa | Merengue</genre>
    <artist></artist>
    <album></album>
    <location>http://streams.calmradio.com:9828/stream</location>
    <rating>3</rating>
    <play-count>4</play-count>
    <last-played>1566038445</last-played>
    <bitrate>128</bitrate>
    <date>0</date>
    <media-type>application/octet-stream</media-type>
  </entry>
  <entry type="iradio">
    <title>Radio Caprice - Doom Metal</title>
    <genre>Doom Metal</genre>
    <artist></artist>
    <album></album>
    <location>http://79.111.14.76:9109/</location>
    <rating>4</rating>
    <play-count>5</play-count>
    <last-played>1547058295</last-played>
    <bitrate>41</bitrate>
    <date>0</date>
    <media-type>application/octet-stream</media-type>
  </entry>
  <entry type="iradio">
    <title>Radio Caprice - Dark Dubstep [x]</title>
    <genre>Dubstep</genre>
    <artist></artist>
    <album></album>
    <location>http://79.120.39.202:9149/</location>
    <rating>4</rating>
    <play-count>7</play-count>
    <last-played>1547057886</last-played>
    <bitrate>37</bitrate>
    <date>0</date>
    <media-type>application/octet-stream</media-type>
  </entry>
  <entry type="iradio">
    <title>Radio Caprice - Brutal Death Metal</title>
    <genre>Brutal Death Metal</genre>
    <artist></artist>
    <album></album>
    <location>http://79.111.119.111:9075/</location>
    <rating>3</rating>
    <play-count>7</play-count>
    <last-played>1567338705</last-played>
    <bitrate>46</bitrate>
    <date>0</date>
    <media-type>application/octet-stream</media-type>
  </entry>
  <entry type="iradio">
    <title>andHow.FM - Got Indie? [!]</title>
    <genre>Indie</genre>
    <artist></artist>
    <album></album>
    <location>http://andhow.org/playlists/andhow.pls</location>
    <rating>4</rating>
    <play-count>23</play-count>
    <last-played>1566026819</last-played>
    <bitrate>128</bitrate>
    <date>0</date>
    <media-type>application/octet-stream</media-type>
  </entry>
  <entry type="iradio">
    <title>Radio Relaxo (128K MP3)</title>
    <genre>Easy Listening</genre>
    <artist></artist>
    <album></album>
    <location>http://69.162.125.2:8318</location>
    <rating>5</rating>
    <play-count>1</play-count>
    <last-played>1567337107</last-played>
    <bitrate>128</bitrate>
    <date>0</date>
    <media-type>application/octet-stream</media-type>
  </entry>
  <entry type="iradio">
    <title>Radio Caprice - Vocal</title>
    <genre>Vocal</genre>
    <artist></artist>
    <album></album>
    <location>http://79.120.77.11:9063/</location>
    <rating>2</rating>
    <play-count>15</play-count>
    <last-played>1567845334</last-played>
    <bitrate>46</bitrate>
    <date>0</date>
    <media-type>application/octet-stream</media-type>
  </entry>
  <entry type="iradio">
    <title>Victoria Halle - 100% Happy Music</title>
    <genre>Pop | Top 40</genre>
    <artist></artist>
    <album></album>
    <location>http://livestream.radiovictoria.be/tijr.m3u</location>
    <rating>3</rating>
    <play-count>22</play-count>
    <last-played>1567339985</last-played>
    <bitrate>191</bitrate>
    <date>0</date>
    <media-type>application/octet-stream</media-type>
  </entry>
  <entry type="iradio">
    <title>Cherry Radio: Tin tuc va Am nhac d0s9</title>
    <genre>vietnamese |hai ngoai | tin tuc</genre>
    <artist></artist>
    <album></album>
    <location>http://192.240.102.133:11973</location>
    <rating>4</rating>
    <play-count>5</play-count>
    <last-played>1567411532</last-played>
    <bitrate>127</bitrate>
    <date>0</date>
    <media-type>application/octet-stream</media-type>
  </entry>
  <entry type="iradio">
    <title>CALM RADIO - AFRICA - Sampler</title>
    <genre>World | African</genre>
    <artist></artist>
    <album></album>
    <location>http://streams.calmradio.com:5128/stream</location>
    <rating>4</rating>
    <play-count>9</play-count>
    <last-played>1566036047</last-played>
    <bitrate>128</bitrate>
    <date>0</date>
    <media-type>application/octet-stream</media-type>
  </entry>
  <entry type="iradio">
    <title>Air FM Gold 0n0</title>
    <genre>Hindi Old | Talk</genre>
    <artist></artist>
    <album></album>
    <location>http://airfmgold-lh.akamaihd.net/i/fmgold_1@507591/master.m3u8</location>
    <rating>2</rating>
    <play-count>20</play-count>
    <last-played>1567331516</last-played>
    <bitrate>50</bitrate>
    <date>0</date>
    <media-type>application/octet-stream</media-type>
  </entry>
  <entry type="iradio">
    <title>G-town Radio: The Sound from Germantown</title>
    <genre>Community Internet Radio</genre>
    <artist></artist>
    <album></album>
    <location>http://www.gtownradio.com/gtown_hi.m3u</location>
    <rating>5</rating>
    <play-count>29</play-count>
    <last-played>1567843503</last-played>
    <bitrate>128</bitrate>
    <date>0</date>
    <media-type>application/octet-stream</media-type>
  </entry>
  <entry type="iradio">
    <title>Death.FM</title>
    <genre>Extreme Metal |Black Metal |Grindcore</genre>
    <artist></artist>
    <album></album>
    <location>http://death.fm/modules/Listen/MP3-hi.pls</location>
    <rating>4</rating>
    <play-count>9</play-count>
    <last-played>1566041176</last-played>
    <bitrate>127</bitrate>
    <date>0</date>
    <media-type>application/octet-stream</media-type>
  </entry>
  <entry type="iradio">
    <title>CALM RADIO - INDIA - Sampler</title>
    <genre>World | Indian | Classical | Fusion | Folk</genre>
    <artist></artist>
    <album></album>
    <location>http://streams.calmradio.com:5328/stream</location>
    <rating>3</rating>
    <play-count>4</play-count>
    <last-played>1566037983</last-played>
    <bitrate>128</bitrate>
    <date>0</date>
    <media-type>application/octet-stream</media-type>
  </entry>
  <entry type="iradio">
    <title>Vividh Bharti [*]</title>
    <genre>Hindi</genre>
    <artist></artist>
    <album></album>
    <location>http://vividhbharati-lh.akamaihd.net/i/vividhbharati_1@507811/master.m3u8</location>
    <rating>3</rating>
    <play-count>4</play-count>
    <last-played>1547191588</last-played>
    <bitrate>52</bitrate>
    <date>0</date>
    <media-type>application/octet-stream</media-type>
  </entry>
  <entry type="iradio">
    <title>psyradio.fm</title>
    <genre>house trance progressive</genre>
    <artist></artist>
    <album></album>
    <location>http://streamer.psyradio.org:8140/listen.pls</location>
    <rating>4</rating>
    <play-count>19</play-count>
    <last-played>1545328618</last-played>
    <bitrate>39</bitrate>
    <date>0</date>
    <media-type>application/octet-stream</media-type>
  </entry>
  <entry type="iradio">
    <title>periszkop radio</title>
    <genre>music</genre>
    <artist></artist>
    <album></album>
    <location>sztrim.periszkopradio.hu:8088/listen.pls</location>
    <rating>4</rating>
    <play-count>10</play-count>
    <last-played>1553437471</last-played>
    <bitrate>192</bitrate>
    <date>0</date>
    <media-type>application/octet-stream</media-type>
  </entry>
  <entry type="iradio">
    <title>GotRadio - RnB Classics</title>
    <genre>RnB</genre>
    <artist></artist>
    <album></album>
    <location>http://pureplay.cdnstream1.com/6023_64.aac</location>
    <rating>4</rating>
    <play-count>3</play-count>
    <last-played>1567311491</last-played>
    <bitrate>55</bitrate>
    <date>0</date>
    <media-type>application/octet-stream</media-type>
  </entry>
  <entry type="iradio">
    <title>Radio Caprice - Russian Pop 80's &amp; 90's</title>
    <genre>Russian Pop</genre>
    <artist></artist>
    <album></album>
    <location>http://79.120.77.11:9015/</location>
    <rating>2</rating>
    <play-count>9</play-count>
    <last-played>1567337783</last-played>
    <bitrate>43</bitrate>
    <date>0</date>
    <media-type>application/octet-stream</media-type>
  </entry>
  <entry type="iradio">
    <title>WMSE [i-]</title>
    <genre>Variety</genre>
    <artist></artist>
    <album></album>
    <location>http://www.wmse.org/wmse128kMP3.pls</location>
    <rating>3</rating>
    <play-count>20</play-count>
    <last-played>1557029908</last-played>
    <bitrate>127</bitrate>
    <date>0</date>
    <media-type>application/octet-stream</media-type>
  </entry>
  <entry type="iradio">
    <title>AIR Radio Kashmir 0n0</title>
    <genre>Kashmiri | Talk</genre>
    <artist></artist>
    <album></album>
    <location>http://kashmiri-lh.akamaihd.net/i/kashmiri_1@528067/master.m3u8</location>
    <rating>3</rating>
    <play-count>14</play-count>
    <last-played>1567335499</last-played>
    <bitrate>46</bitrate>
    <date>0</date>
    <media-type>application/octet-stream</media-type>
  </entry>
  <entry type="iradio">
    <title>KWVA 0n0</title>
    <genre>Student | Eclectic</genre>
    <artist></artist>
    <album></album>
    <location>http://kwvaradio.uoregon.edu:8000/listen.pls</location>
    <rating>2</rating>
    <play-count>41</play-count>
    <last-played>1567845424</last-played>
    <bitrate>127</bitrate>
    <date>0</date>
    <media-type>application/octet-stream</media-type>
  </entry>
  <entry type="iradio">
    <title>Radio Caprice - Experimental Music</title>
    <genre>Experimental</genre>
    <artist></artist>
    <album></album>
    <location>http://79.111.119.111:9109/</location>
    <rating>4</rating>
    <play-count>9</play-count>
    <last-played>1547186879</last-played>
    <bitrate>59</bitrate>
    <date>0</date>
    <media-type>application/octet-stream</media-type>
  </entry>
  <entry type="iradio">
    <title>Blue Heron Radio</title>
    <genre>World | Japanese</genre>
    <artist></artist>
    <album></album>
    <location>http://www.blueheronradio.com/playlists/BlueHeronRadio.pls</location>
    <rating>5</rating>
    <play-count>39</play-count>
    <last-played>1566099705</last-played>
    <bitrate>128</bitrate>
    <date>0</date>
    <media-type>application/octet-stream</media-type>
  </entry>
  <entry type="iradio">
    <title>Radio Caprice - Dark Jazz</title>
    <genre>Dark Jazz</genre>
    <artist></artist>
    <album></album>
    <location>http://79.120.39.202:9137/</location>
    <rating>4</rating>
    <play-count>7</play-count>
    <last-played>1547057967</last-played>
    <bitrate>46</bitrate>
    <date>0</date>
    <media-type>application/octet-stream</media-type>
  </entry>
  <entry type="iradio">
    <title>Radio Caprice - Suomisaundi</title>
    <genre>Suomisaundi</genre>
    <artist></artist>
    <album></album>
    <location>http://79.120.77.11:9147/</location>
    <rating>3</rating>
    <play-count>11</play-count>
    <last-played>1567338989</last-played>
    <bitrate>45</bitrate>
    <date>0</date>
    <media-type>application/octet-stream</media-type>
  </entry>
  <entry type="iradio">
    <title>RadioSindhi.com PRIME</title>
    <genre>Pop | Talk</genre>
    <artist></artist>
    <album></album>
    <location>http://139.59.119.157:8211</location>
    <play-count>21</play-count>
    <last-played>1567874946</last-played>
    <bitrate>31</bitrate>
    <date>0</date>
    <media-type>application/octet-stream</media-type>
  </entry>
  <entry type="iradio">
    <title>Mirchi</title>
    <genre>Bollywood | Hindi | Talk</genre>
    <artist></artist>
    <album></album>
    <location>http://peridot.streamguys.com:7150/Mirchi</location>
    <rating>2</rating>
    <play-count>3</play-count>
    <last-played>1567337972</last-played>
    <bitrate>28</bitrate>
    <date>0</date>
    <media-type>application/octet-stream</media-type>
  </entry>
  <entry type="iradio">
    <title>RadiOi</title>
    <genre>Oi | Punk</genre>
    <artist></artist>
    <album></album>
    <location>http://cp.eu4.fastcast4u.com:2199/tunein/nikoud00.pls</location>
    <rating>3</rating>
    <play-count>24</play-count>
    <last-played>1567339899</last-played>
    <bitrate>127</bitrate>
    <date>0</date>
    <media-type>application/octet-stream</media-type>
  </entry>
  <entry type="iradio">
    <title>NadamRadio</title>
    <genre>Hindu Devotional Malayalam</genre>
    <artist></artist>
    <album></album>
    <location>http://viadj.viastreaming.net:7070/</location>
    <rating>3</rating>
    <play-count>16</play-count>
    <last-played>1547191605</last-played>
    <bitrate>128</bitrate>
    <date>0</date>
    <media-type>application/octet-stream</media-type>
  </entry>
  <entry type="iradio">
    <title>Radio Caprice - Progressive Black/Post-Black</title>
    <genre>Progressive Black/Post-Black</genre>
    <artist></artist>
    <album></album>
    <location>http://79.111.14.76:9131/</location>
    <rating>4</rating>
    <play-count>8</play-count>
    <last-played>1559391972</last-played>
    <bitrate>47</bitrate>
    <date>0</date>
    <media-type>application/octet-stream</media-type>
  </entry>
  <entry type="iradio">
    <title>Radioasia 1269 AM 0n0 d0s!</title>
    <genre>Malayalam | Talk</genre>
    <artist></artist>
    <album></album>
    <location>http://50.7.71.27:9699/</location>
    <rating>3</rating>
    <play-count>29</play-count>
    <last-played>1567410293</last-played>
    <bitrate>95</bitrate>
    <date>0</date>
    <media-type>application/octet-stream</media-type>
  </entry>
  <entry type="iradio">
    <title>Radio Caprice - Ethno Jazz</title>
    <genre>Ethno Jazz</genre>
    <artist></artist>
    <album></album>
    <location>http://79.120.39.202:9157/</location>
    <rating>3</rating>
    <play-count>10</play-count>
    <last-played>1567338948</last-played>
    <bitrate>65</bitrate>
    <date>0</date>
    <media-type>application/octet-stream</media-type>
  </entry>
  <entry type="iradio">
    <title>SUPER FM Turkey</title>
    <genre>Turkish Pop</genre>
    <artist></artist>
    <album></album>
    <location>http://17753.live.streamtheworld.com/SUPER_FMAAC_SC</location>
    <rating>3</rating>
    <play-count>7</play-count>
    <last-played>1567338153</last-played>
    <bitrate>57</bitrate>
    <date>0</date>
    <media-type>application/octet-stream</media-type>
  </entry>
  <entry type="iradio">
    <title>Radio Caprice - Industrial Metal</title>
    <genre>Industrial Metal</genre>
    <artist></artist>
    <album></album>
    <location>http://79.120.39.202:9075/</location>
    <rating>3</rating>
    <play-count>9</play-count>
    <last-played>1567338854</last-played>
    <bitrate>46</bitrate>
    <date>0</date>
    <media-type>application/octet-stream</media-type>
  </entry>
  <entry type="iradio">
    <title>TrueBlackMetalRadio</title>
    <genre>Black Metal</genre>
    <artist></artist>
    <album></album>
    <location>http://trueblackmetalradio.com:666/radio.m3u</location>
    <rating>4</rating>
    <play-count>3</play-count>
    <last-played>1557029672</last-played>
    <bitrate>128</bitrate>
    <date>0</date>
    <media-type>application/octet-stream</media-type>
  </entry>
  <entry type="iradio">
    <title>Radio Caprice - Black Metal</title>
    <genre>Black Metal</genre>
    <artist></artist>
    <album></album>
    <location>http://79.120.77.11:9003/</location>
    <rating>4</rating>
    <play-count>8</play-count>
    <last-played>1547057780</last-played>
    <bitrate>43</bitrate>
    <date>0</date>
    <media-type>application/octet-stream</media-type>
  </entry>
  <entry type="iradio">
    <title>Radio Oira</title>
    <genre>Ethno Latvian Folk World</genre>
    <artist></artist>
    <album></album>
    <location>http://www.radiooira.lv/folk.pls</location>
    <rating>4</rating>
    <play-count>14</play-count>
    <last-played>1545132746</last-played>
    <bitrate>128</bitrate>
    <date>0</date>
    <media-type>application/octet-stream</media-type>
  </entry>
  <entry type="iradio">
    <title>GotRadio - OG's Hip Hop and RnB</title>
    <genre>Hip Hop | Rap | RnB</genre>
    <artist></artist>
    <album></album>
    <location>http://pureplay.cdnstream1.com/6045_128.mp3</location>
    <rating>3</rating>
    <play-count>6</play-count>
    <last-played>1567311819</last-played>
    <bitrate>128</bitrate>
    <date>0</date>
    <media-type>application/octet-stream</media-type>
  </entry>
  <entry type="iradio">
    <title>Radio Caprice - Indian Folk</title>
    <genre>Indian</genre>
    <artist></artist>
    <album></album>
    <location>http://79.111.14.76:9021/</location>
    <rating>3</rating>
    <play-count>16</play-count>
    <last-played>1567858192</last-played>
    <bitrate>41</bitrate>
    <date>0</date>
    <media-type>application/octet-stream</media-type>
  </entry>
  <entry type="iradio">
    <title>Tamil FM Sri Lanka</title>
    <genre>Unknown</genre>
    <artist></artist>
    <album></album>
    <location>http://shaincast.caster.fm:47814/listen.mp3</location>
    <play-count>3</play-count>
    <last-played>1567850790</last-played>
    <bitrate>128</bitrate>
    <date>0</date>
    <media-type>application/octet-stream</media-type>
  </entry>
  <entry type="iradio">
    <title>Radio Caprice - Jazz Manouche</title>
    <genre>Gypsy Jazz</genre>
    <artist></artist>
    <album></album>
    <location>http://79.120.77.11:9129/</location>
    <rating>4</rating>
    <play-count>7</play-count>
    <last-played>1558019775</last-played>
    <bitrate>44</bitrate>
    <date>0</date>
    <media-type>application/octet-stream</media-type>
  </entry>
  <entry type="iradio">
    <title>Radio Caprice - Russian Folk</title>
    <genre>Russian Folk</genre>
    <artist></artist>
    <album></album>
    <location>http://79.120.77.11:9057/</location>
    <rating>4</rating>
    <play-count>9</play-count>
    <last-played>1547057744</last-played>
    <bitrate>47</bitrate>
    <date>0</date>
    <media-type>application/octet-stream</media-type>
  </entry>
  <entry type="iradio">
    <title>Radio Caprice - Oriental Metal</title>
    <genre>Oriental Metal</genre>
    <artist></artist>
    <album></album>
    <location>http://79.111.119.111:9145/</location>
    <rating>3</rating>
    <play-count>14</play-count>
    <last-played>1567338769</last-played>
    <bitrate>40</bitrate>
    <date>0</date>
    <media-type>application/octet-stream</media-type>
  </entry>
  <entry type="iradio">
    <title>GotRadio - Native American</title>
    <genre>Native American</genre>
    <artist></artist>
    <album></album>
    <location>http://pureplay.cdnstream1.com/6022_128.mp3</location>
    <rating>4</rating>
    <play-count>4</play-count>
    <last-played>1559380082</last-played>
    <bitrate>128</bitrate>
    <date>0</date>
    <media-type>application/octet-stream</media-type>
  </entry>
  <entry type="iradio">
    <title>Organon Radio</title>
    <genre>Classical | Organ</genre>
    <artist></artist>
    <album></album>
    <location>http://208.131.139.148:8062/stream</location>
    <play-count>1</play-count>
    <last-played>1567878030</last-played>
    <bitrate>128</bitrate>
    <date>0</date>
    <media-type>application/octet-stream</media-type>
  </entry>
  <entry type="iradio">
    <title>WFMU Freeform Radio</title>
    <genre>Community</genre>
    <artist></artist>
    <album></album>
    <location>http://wfmu.org/wfmu.pls</location>
    <rating>4</rating>
    <play-count>12</play-count>
    <last-played>1545132705</last-played>
    <bitrate>128</bitrate>
    <date>0</date>
    <media-type>application/octet-stream</media-type>
  </entry>
  <entry type="iradio">
    <title>Air Urdu 0n0</title>
    <genre>Urdu</genre>
    <artist></artist>
    <album></album>
    <location>http://airurdu-lh.akamaihd.net/i/airurdu_1@507813/master.m3u8</location>
    <rating>3</rating>
    <play-count>9</play-count>
    <last-played>1547193931</last-played>
    <bitrate>48</bitrate>
    <date>0</date>
    <media-type>application/octet-stream</media-type>
  </entry>
  <entry type="iradio">
    <title>Music Of India Radio (128K MP3)</title>
    <genre>World</genre>
    <artist></artist>
    <album></album>
    <location>http://69.162.125.2:8260/</location>
    <play-count>2</play-count>
    <last-played>1567401079</last-played>
    <bitrate>128</bitrate>
    <date>0</date>
    <media-type>application/octet-stream</media-type>
  </entry>
  <entry type="iradio">
    <title>GotRadio - Piano Perfect</title>
    <genre>Piano</genre>
    <artist></artist>
    <album></album>
    <location>http://pureplay.cdnstream1.com/6017_128.mp3</location>
    <rating>3</rating>
    <play-count>4</play-count>
    <last-played>1559030506</last-played>
    <bitrate>128</bitrate>
    <date>0</date>
    <media-type>application/octet-stream</media-type>
  </entry>
  <entry type="iradio">
    <title>CALM RADIO - TIBET - Sampler</title>
    <genre>World | Asian | Tibet</genre>
    <artist></artist>
    <album></album>
    <location>http://streams.calmradio.com:6528/stream</location>
    <rating>3</rating>
    <play-count>13</play-count>
    <last-played>1566039729</last-played>
    <bitrate>128</bitrate>
    <date>0</date>
    <media-type>application/octet-stream</media-type>
  </entry>
  <entry type="iradio">
    <title>Radio Paradise</title>
    <genre>Eclectic</genre>
    <artist></artist>
    <album></album>
    <location>http://stream.radioparadise.com/aac-320</location>
    <rating>5</rating>
    <play-count>1</play-count>
    <last-played>1567329626</last-played>
    <bitrate>322</bitrate>
    <date>0</date>
    <media-type>application/octet-stream</media-type>
  </entry>
  <entry type="iradio">
    <title>Radio Paradise Eclectic</title>
    <genre>Eclectic</genre>
    <artist></artist>
    <album></album>
    <location>http://stream.radioparadise.com/eclectic-320</location>
    <rating>5</rating>
    <play-count>1</play-count>
    <last-played>1567330109</last-played>
    <bitrate>318</bitrate>
    <date>0</date>
    <media-type>application/octet-stream</media-type>
  </entry>
  <entry type="iradio">
    <title>Radio Arcadia (128K MP3)</title>
    <genre>Eclectic</genre>
    <artist></artist>
    <album></album>
    <location>http://69.162.125.2:8246</location>
    <rating>5</rating>
    <play-count>1</play-count>
    <last-played>1567336827</last-played>
    <bitrate>128</bitrate>
    <date>0</date>
    <media-type>application/octet-stream</media-type>
  </entry>
  <entry type="iradio">
    <title>Radio Synthetique (128AAC+)</title>
    <genre>Eclectic</genre>
    <artist></artist>
    <album></album>
    <location>http://208.131.139.148:8083/stream</location>
    <play-count>3</play-count>
    <last-played>1567877630</last-played>
    <bitrate>127</bitrate>
    <date>0</date>
    <media-type>application/octet-stream</media-type>
  </entry>
  <entry type="iradio">
    <title>KCRW E24</title>
    <genre>Eclectic</genre>
    <artist></artist>
    <album></album>
    <location>https://kcrw.streamguys1.com/kcrw_192k_mp3_e24</location>
    <rating>5</rating>
    <play-count>15</play-count>
    <last-played>1567418548</last-played>
    <bitrate>191</bitrate>
    <date>0</date>
    <media-type>application/octet-stream</media-type>
  </entry>
  <entry type="iradio">
    <title>KEXP.ORG 90.3FM - where the music matters</title>
    <genre>Eclectic</genre>
    <artist></artist>
    <album></album>
    <location>http://live-aacplus-64.kexp.org/kexp64.aac</location>
    <rating>5</rating>
    <play-count>27</play-count>
    <last-played>1567340343</last-played>
    <bitrate>62</bitrate>
    <date>0</date>
    <media-type>application/octet-stream</media-type>
  </entry>
  <entry type="iradio">
    <title>KFJC 192k AAC-LC</title>
    <genre>Eclectic</genre>
    <artist></artist>
    <album></album>
    <location>http://aac.kfjc.org/listen.pls</location>
    <rating>5</rating>
    <play-count>15</play-count>
    <last-played>1545136235</last-played>
    <bitrate>182</bitrate>
    <date>0</date>
    <media-type>application/octet-stream</media-type>
  </entry>
  <entry type="iradio">
    <title>CALM RADIO - FENG SHUI - Sampler</title>
    <genre>New Age | Easy Listening | Ambient</genre>
    <artist></artist>
    <album></album>
    <location>http://streams.calmradio.com:20228/stream</location>
    <rating>3</rating>
    <play-count>4</play-count>
    <last-played>1566037991</last-played>
    <bitrate>128</bitrate>
    <date>0</date>
    <media-type>application/octet-stream</media-type>
  </entry>
  <entry type="iradio">
    <title>AIR Ragam [*]</title>
    <genre>Indian Classical</genre>
    <artist></artist>
    <album></album>
    <location>http://airraagam-lh.akamaihd.net/i/airraagam_1@507820/master.m3u8</location>
    <rating>4</rating>
    <play-count>21</play-count>
    <last-played>1566300913</last-played>
    <bitrate>46</bitrate>
    <date>0</date>
    <media-type>application/octet-stream</media-type>
  </entry>
  <entry type="ignore">
    <title></title>
    <genre></genre>
    <artist></artist>
    <album></album>
    <location>file:///home/evol/Music/Ancient%20Kurdish%20(Medes)%20folk%20songs%20-%20Kurds%20and%20Kurdistan-HxvIShInqyY.mp4</location>
    <mtime>1448871072</mtime>
    <date>0</date>
    <media-type>application/octet-stream</media-type>
  </entry>
  <entry type="ignore">
    <title></title>
    <genre></genre>
    <artist></artist>
    <album></album>
    <location>file:///home/evol/Music/The%20music%20of%20%20Komitas%20-%20Armenian%20classic%20folk%20music-x1-fNQaHEt4.mkv</location>
    <mtime>1451676933</mtime>
    <date>0</date>
    <media-type>application/octet-stream</media-type>
  </entry>
  <entry type="ignore">
    <title></title>
    <genre></genre>
    <artist></artist>
    <album></album>
    <location>file:///home/evol/Music/Unsorted/Outgoing_Call%20-%20+919496208217%20-%2020160827_162605.amr</location>
    <mtime>1472295365</mtime>
    <date>0</date>
    <media-type>application/octet-stream</media-type>
  </entry>
  <entry type="ignore">
    <title></title>
    <genre></genre>
    <artist></artist>
    <album></album>
    <location>file:///home/evol/Music/Unsorted/Outgoing_Call%20-%20Punjabi_Roots%20-%2020160811_213119.amr</location>
    <mtime>1470931279</mtime>
    <date>0</date>
    <media-type>application/octet-stream</media-type>
  </entry>
  <entry type="ignore">
    <title></title>
    <genre></genre>
    <artist></artist>
    <album></album>
    <location>file:///home/evol/Music/Unsorted/Outgoing_Call%20-%20Sumanth_Cnsss%20-%2020160807_215239.amr</location>
    <mtime>1470586959</mtime>
    <date>0</date>
    <media-type>application/octet-stream</media-type>
  </entry>
  <entry type="ignore">
    <title></title>
    <genre></genre>
    <artist></artist>
    <album></album>
    <location>file:///home/evol/Music/Unsorted/Outgoing_Call%20-%20+918424057984%20-%2020160707_111028.amr</location>
    <mtime>1467870028</mtime>
    <date>0</date>
    <media-type>application/octet-stream</media-type>
  </entry>
  <entry type="ignore">
    <title></title>
    <genre></genre>
    <artist></artist>
    <album></album>
    <location>file:///home/evol/Music/Jim%20Croce%20%20-%20Photographs%20And%20Memories-48o5rCFFxh8.mp4</location>
    <mtime>1394262617</mtime>
    <date>0</date>
    <media-type>application/octet-stream</media-type>
  </entry>
  <entry type="ignore">
    <title></title>
    <genre></genre>
    <artist></artist>
    <album></album>
    <location>file:///home/evol/Music/Anguli%20sparsham%20Jayalakshmi%20singing-QHltCN9qhtw.mkv</location>
    <mtime>1475817175</mtime>
    <date>0</date>
    <media-type>application/octet-stream</media-type>
  </entry>
  <entry type="ignore">
    <title></title>
    <genre></genre>
    <artist></artist>
    <album></album>
    <location>file:///home/evol/Music/Yatra%20_%20Tribute%20to%20Ilayaraja%20_%20Cover%20by%20Rakeeb-3Q_5m2q1v9M.mp4</location>
    <mtime>1491161359</mtime>
    <date>0</date>
    <media-type>application/octet-stream</media-type>
  </entry>
  <entry type="ignore">
    <title></title>
    <genre></genre>
    <artist></artist>
    <album></album>
    <location>file:///home/evol/Music/Old%20Armenian%20folk%20songs%20-%20Real%20Armenian%20music-YRjxlU5EM_Y.mkv</location>
    <mtime>1449415429</mtime>
    <date>0</date>
    <media-type>application/octet-stream</media-type>
  </entry>
  <entry type="ignore">
    <title></title>
    <genre></genre>
    <artist></artist>
    <album></album>
    <location>file:///home/evol/Music/Unsorted/Incoming_Call%20-%20+918424057984%20-%2020160707_111644.amr</location>
    <mtime>1467870404</mtime>
    <date>0</date>
    <media-type>application/octet-stream</media-type>
  </entry>
  <entry type="ignore">
    <title></title>
    <genre></genre>
    <artist></artist>
    <album></album>
    <location>file:///home/evol/Music/Bolot%20&amp;%20Nohon%20-%20Maadai-Kara-iq990wTR40M.mkv</location>
    <mtime>1419326200</mtime>
    <date>0</date>
    <media-type>application/octet-stream</media-type>
  </entry>
  <entry type="ignore">
    <title></title>
    <genre></genre>
    <artist></artist>
    <album></album>
    <location>file:///home/evol/Music/Unsorted/Outgoing_Call%20-%20Sumanth_Cnsss%20-%2020160807_215227.amr</location>
    <mtime>1470586947</mtime>
    <date>0</date>
    <media-type>application/octet-stream</media-type>
  </entry>
  <entry type="ignore">
    <title></title>
    <genre></genre>
    <artist></artist>
    <album></album>
    <location>file:///home/evol/Music/Unsorted/Outgoing_Call%20-%20Sumanth_Cnsss%20-%2020160807_215216.amr</location>
    <mtime>1470586936</mtime>
    <date>0</date>
    <media-type>application/octet-stream</media-type>
  </entry>
  <entry type="ignore">
    <title></title>
    <genre></genre>
    <artist></artist>
    <album></album>
    <location>file:///home/evol/Music/%E1%83%90%E1%83%AD%E1%83%90%E1%83%A0%E1%83%A3%E1%83%9A%E1%83%98%20%E1%83%92%E1%83%90%E1%83%9C%E1%83%93%E1%83%90%E1%83%92%E1%83%90%E1%83%9C%E1%83%90%20(%E1%83%9E%E1%83%9D%E1%83%9E%E1%83%A3%E1%83%A0%E1%83%98)-Bv8NQpzeJ7c.mkv</location>
    <mtime>1429952375</mtime>
    <date>0</date>
    <media-type>application/octet-stream</media-type>
  </entry>
</rhythmdb>
